<?xml version="1.0" encoding="utf-8"?>
<annotation>
	<folder>VOC2007</folder>
	<filename>133.jpg</filename>
	<source>
		<database>The VOC2007 Database</database>
	</source>
	<owner>
		<name>AM</name>
	</owner>
	<segmented>0</segmented>
	<size>
		<width>3072</width>
		<height>2048</height>
	</size>
	<object>
		<pose>frontal</pose>
		<truncated>0</truncated>
		<difficult>0</difficult>
		<name>wood</name>
		<bndbox>
			<xmin>128</xmin>
			<ymin>1157</ymin>
			<xmax>368</xmax>
			<ymax>1385</ymax>
		</bndbox>
	</object>
	<object>
		<pose>frontal</pose>
		<truncated>0</truncated>
		<difficult>0</difficult>
		<name>wood</name>
		<bndbox>
			<xmin>544</xmin>
			<ymin>1041</ymin>
			<xmax>789</xmax>
			<ymax>1283</ymax>
		</bndbox>
	</object>
	<object>
		<pose>frontal</pose>
		<truncated>0</truncated>
		<difficult>0</difficult>
		<name>wood</name>
		<bndbox>
			<xmin>986</xmin>
			<ymin>1175</ymin>
			<xmax>1228</xmax>
			<ymax>1412</ymax>
		</bndbox>
	</object>
	<object>
		<pose>frontal</pose>
		<truncated>0</truncated>
		<difficult>0</difficult>
		<name>wood</name>
		<bndbox>
			<xmin>1418</xmin>
			<ymin>1075</ymin>
			<xmax>1668</xmax>
			<ymax>1314</ymax>
		</bndbox>
	</object>
	<object>
		<pose>frontal</pose>
		<truncated>0</truncated>
		<difficult>0</difficult>
		<name>wood</name>
		<bndbox>
			<xmin>1852</xmin>
			<ymin>1012</ymin>
			<xmax>2107</xmax>
			<ymax>1259</ymax>
		</bndbox>
	</object>
	<object>
		<pose>frontal</pose>
		<truncated>0</truncated>
		<difficult>0</difficult>
		<name>wood</name>
		<bndbox>
			<xmin>2276</xmin>
			<ymin>1135</ymin>
			<xmax>2528</xmax>
			<ymax>1375</ymax>
		</bndbox>
	</object>
</annotation>
