<?xml version="1.0" encoding="utf-8"?>
<annotation>
	<folder>VOC2007</folder>
	<filename>247.jpg</filename>
	<source>
		<database>The VOC2007 Database</database>
	</source>
	<owner>
		<name>AM</name>
	</owner>
	<segmented>0</segmented>
	<size>
		<width>3072</width>
		<height>2048</height>
	</size>
	<object>
		<pose>frontal</pose>
		<truncated>0</truncated>
		<difficult>0</difficult>
		<name>wood</name>
		<bndbox>
			<xmin>678</xmin>
			<ymin>1059</ymin>
			<xmax>936</xmax>
			<ymax>1312</ymax>
		</bndbox>
	</object>
	<object>
		<pose>frontal</pose>
		<truncated>0</truncated>
		<difficult>0</difficult>
		<name>wood</name>
		<bndbox>
			<xmin>1039</xmin>
			<ymin>1122</ymin>
			<xmax>1294</xmax>
			<ymax>1372</ymax>
		</bndbox>
	</object>
	<object>
		<pose>frontal</pose>
		<truncated>0</truncated>
		<difficult>0</difficult>
		<name>wood</name>
		<bndbox>
			<xmin>1452</xmin>
			<ymin>1154</ymin>
			<xmax>1689</xmax>
			<ymax>1393</ymax>
		</bndbox>
	</object>
	<object>
		<pose>frontal</pose>
		<truncated>0</truncated>
		<difficult>0</difficult>
		<name>wood</name>
		<bndbox>
			<xmin>1905</xmin>
			<ymin>1178</ymin>
			<xmax>2150</xmax>
			<ymax>1401</ymax>
		</bndbox>
	</object>
	<object>
		<pose>frontal</pose>
		<truncated>0</truncated>
		<difficult>0</difficult>
		<name>wood</name>
		<bndbox>
			<xmin>2339</xmin>
			<ymin>1064</ymin>
			<xmax>2576</xmax>
			<ymax>1301</ymax>
		</bndbox>
	</object>
	<object>
		<pose>frontal</pose>
		<truncated>0</truncated>
		<difficult>0</difficult>
		<name>wood</name>
		<bndbox>
			<xmin>2750</xmin>
			<ymin>1188</ymin>
			<xmax>2989</xmax>
			<ymax>1420</ymax>
		</bndbox>
	</object>
</annotation>
