<?xml version="1.0" encoding="utf-8"?>
<annotation>
	<folder>VOC2007</folder>
	<filename>a82.jpg</filename>
	<source>
		<database>The VOC2007 Database</database>
	</source>
	<owner>
		<name>AM</name>
	</owner>
	<segmented>0</segmented>
	<size>
		<width>3072</width>
		<height>2048</height>
	</size>
	<object>
		<pose>frontal</pose>
		<truncated>0</truncated>
		<difficult>0</difficult>
		<name>wood</name>
		<bndbox>
			<xmin>123</xmin>
			<ymin>1085</ymin>
			<xmax>356</xmax>
			<ymax>1312</ymax>
		</bndbox>
	</object>
	<object>
		<pose>frontal</pose>
		<truncated>0</truncated>
		<difficult>0</difficult>
		<name>wood</name>
		<bndbox>
			<xmin>453</xmin>
			<ymin>1093</ymin>
			<xmax>718</xmax>
			<ymax>1317</ymax>
		</bndbox>
	</object>
	<object>
		<pose>frontal</pose>
		<truncated>0</truncated>
		<difficult>0</difficult>
		<name>wood</name>
		<bndbox>
			<xmin>842</xmin>
			<ymin>1090</ymin>
			<xmax>1113</xmax>
			<ymax>1328</ymax>
		</bndbox>
	</object>
	<object>
		<pose>frontal</pose>
		<truncated>0</truncated>
		<difficult>0</difficult>
		<name>wood</name>
		<bndbox>
			<xmin>1261</xmin>
			<ymin>1085</ymin>
			<xmax>1542</xmax>
			<ymax>1328</ymax>
		</bndbox>
	</object>
	<object>
		<pose>frontal</pose>
		<truncated>0</truncated>
		<difficult>0</difficult>
		<name>wood</name>
		<bndbox>
			<xmin>1707</xmin>
			<ymin>1082</ymin>
			<xmax>1986</xmax>
			<ymax>1312</ymax>
		</bndbox>
	</object>
	<object>
		<pose>frontal</pose>
		<truncated>0</truncated>
		<difficult>0</difficult>
		<name>wood</name>
		<bndbox>
			<xmin>2142</xmin>
			<ymin>1090</ymin>
			<xmax>2415</xmax>
			<ymax>1323</ymax>
		</bndbox>
	</object>
	<object>
		<pose>frontal</pose>
		<truncated>0</truncated>
		<difficult>0</difficult>
		<name>wood</name>
		<bndbox>
			<xmin>2556</xmin>
			<ymin>1093</ymin>
			<xmax>2818</xmax>
			<ymax>1323</ymax>
		</bndbox>
	</object>
	<object>
		<pose>frontal</pose>
		<truncated>0</truncated>
		<difficult>0</difficult>
		<name>wood</name>
		<bndbox>
			<xmin>2956</xmin>
			<ymin>1101</ymin>
			<xmax>3071</xmax>
			<ymax>1333</ymax>
		</bndbox>
	</object>
</annotation>
